vcf_subset-2.0.0.dist-info/METADATA
vcf_subset-2.0.0.dist-info/WHEEL
vcf_subset.libs/libgcc_s-5b5488a6.so.1
vcf_subset/__init__.py
vcf_subset/vcf_subset.pypy39-pp73-arm-linux-gnu.so
vcf_subset-2.0.0.dist-info/RECORD
